SimpleRegressor/__init__.py
SimpleRegressor/functions.py
SimpleRegressor/encoders/__init__.py
SimpleRegressor/encoders/encoder_dict.pkl
SimpleRegressor/pre_trained_models/__init__.py
SimpleRegressor/pre_trained_models/regressor.pkl
SimpleRegressor-0.0.1.dist-info/METADATA
SimpleRegressor-0.0.1.dist-info/WHEEL
SimpleRegressor-0.0.1.dist-info/top_level.txt
SimpleRegressor-0.0.1.dist-info/RECORD
